{
  "subNodes": [
    {
      "idNum": 0,
      "orderNum": 0,
      "pcNode": true,
      "linkTo": 0,
      "ShowOnlyOnce": false,
      "NodeIsActive": true,
      "NodePortraitBitmap": "",
      "NodeNpcName": "",
      "NodeSound": "none",
      "conversationText": "root",
      "IsExpanded": true,
      "subNodes": [
        {
          "idNum": 1,
          "orderNum": 0,
          "pcNode": false,
          "linkTo": 0,
          "ShowOnlyOnce": false,
          "NodeIsActive": true,
          "NodePortraitBitmap": "",
          "NodeNpcName": "",
          "NodeSound": "none",
          "conversationText": "The ceiling to this once great room has collapsed, with broken masonry blocking any progress. The room must once have been the great prayer room. You can just about make out rows of benches, and, at the far end and shrouded in gloom, an old altar.",
          "IsExpanded": true,
          "subNodes": [
            {
              "idNum": 2,
              "orderNum": 0,
              "pcNode": true,
              "linkTo": 0,
              "ShowOnlyOnce": false,
              "NodeIsActive": true,
              "NodePortraitBitmap": "",
              "NodeNpcName": "",
              "NodeSound": "none",
              "conversationText": "Continue",
              "IsExpanded": true,
              "subNodes": [],
              "actions": [],
              "conditions": [],
              "isLink": false
            }
          ],
          "actions": [],
          "conditions": [],
          "isLink": false
        }
      ],
      "actions": [],
      "conditions": [],
      "isLink": false
    }
  ],
  "ConvoFileName": "1 Main Chamber",
  "Narration": false,
  "PartyChat": false,
  "SpeakToMainPcOnly": false,
  "NpcPortraitBitmap": "1templepews.png",
  "DefaultNpcName": "",
  "NextIdNum": 2
}